pyiku/__init__.py
pyiku/_info.py
pyiku/main.py
pyiku-0.0.2.dist-info/LICENSE
pyiku-0.0.2.dist-info/METADATA
pyiku-0.0.2.dist-info/WHEEL
pyiku-0.0.2.dist-info/top_level.txt
pyiku-0.0.2.dist-info/RECORD
